{"slug":"hindi-hip-hop","name":"hindi hip hop","artists":[{"name":"Yo Yo Honey Singh","id":"7uIbLdzzSEqnX0Pkrb56cR"},{"name":"King","id":"5NHm4TU5Twz7owibYxJfFU"},{"name":"Talha Anjum","id":"69xcFpmqTOmFNOL08Bxyci"},{"name":"KR$NA","id":"5C1S9XwxMuuCciutwMhp5t"},{"name":"DIVINE","id":"4Ai0pGz6GhQavjzaRhPTvz"},{"name":"Ranveer Singh","id":"0lMa3YTHqQnDDTBaxAV7LK"},{"name":"Seedhe Maut","id":"2oBG74gAocPMFv6Ij9ykdo"},{"name":"Emiway Bantai","id":"008PpLcKUtVXle6JSwkq3I"},{"name":"Raftaar","id":"5UdFr0GeO7jKIaNIJgwB36"},{"name":"Yashraj","id":"0TwG8C39WJIfFlcPrhxHST"},{"name":"Nucleya","id":"2CkrXQPoBz8jTQ3u0ZeLPh"},{"name":"Baba Sehgal","id":"7hYZXC29LqX4vWGloviTyG"},{"name":"Bharg","id":"5mUENA9ewpJd5z9KuwOKrd"},{"name":"Ajey Nagar (CarryMinati)","id":"1VwNP7mP5DmTsdJqQuW0nT"},{"name":"Panther","id":"1HnV8VaGdip3y1SpJPgft0"},{"name":"Rawal","id":"3XbsFoxsYfrJyo9VZrbM16"},{"name":"Bandish Projekt","id":"0nFWwB5eQCvOdqGRlWVqBK"},{"name":"Dank Rishu","id":"352KPlYGQPAPpvAt8tnilG"},{"name":"Gravity","id":"7ti25GJHIRWZ5f1WN0T2zO"},{"name":"yungsta","id":"4HQz6xUrKEKQ8nmMKsfvkB"}],"related":["desi hip hop","desi trap","indian underground rap","albanian hip hop","polish viral rap","rap salvadoreno","rap sardegna","khmer hip hop","pop catracho","afrikaans hip hop","trap colombiano","afghan rap","pinoy alternative rap","korean underground rap","rap motywacja","danish hip hop","rap canario","nz gangsta rap","mexican hip hop","punjabi hip hop"]}