{"slug":"jazz-clarinet","name":"jazz clarinet","artists":[{"name":"Benny Goodman","id":"1pBuKaLHJlIlqYxQQaflve"},{"name":"Artie Shaw","id":"5wam12nGWDBIrLDV78TNSF"},{"name":"Sidney Bechet","id":"1RsmXc1ZqW3WBs9iwxiSwk"},{"name":"Acker Bilk","id":"5bdgb81IJMXag724quaNSA"},{"name":"Benny Goodman Quartet","id":"26vAEAV08relvScS4FUsIt"},{"name":"Jimmy Giuffre","id":"4RncsrNJ1GDGsFBIxI76L6"},{"name":"Jimmy Dorsey","id":"3xPpQCRiTBxgmL4PD8J5ek"},{"name":"Eddie Daniels","id":"3ISnQ3eaEt4SEnd7GSInCO"},{"name":"Johnny Dodds","id":"5Epg9knob31gEXJGg9V5Sp"},{"name":"Pete Fountain","id":"60dYNEvXzIl38BKZoW8HYd"},{"name":"Rolf Kühn","id":"73xPAo16RiiVu6X90p7UVb"},{"name":"Tony Scott","id":"3wtfcI8iPGKBmnalt0013v"},{"name":"Monty Sunshine","id":"42AJfxnbtIFT4DbZcUf11d"},{"name":"Bobby Gordon","id":"0oPMW9GPyDmrhlQx1ZxfuK"},{"name":"Don Byron","id":"2xJ2HMpwwLY36bkjT6sJkD"},{"name":"George Lewis","id":"7mleIOAroBQWqO7SNrAUlt"},{"name":"Sid Phillips","id":"33Esqj5IXYL4uVyhFc3yKS"},{"name":"Hubert Rostaing","id":"7zM3bs7txo1TnD1psGGfQc"},{"name":"Edmond Hall","id":"0ObFsHKsujQRFXqEL6Q0Jc"},{"name":"Buddy DeFranco","id":"4PGmuM1NRpb2AynvthlC6y"}],"related":["new orleans jazz","dixieland","big band","vintage jazz","french jazz","boogie-woogie","jazz trombone","hot jazz","swing","african-american classical","barrelhouse piano","bebop","blaskapelle","blasmusik","carnatic instrumental","choro","czech swing","dechovka","dombra","ethnomusicology"]}