{"slug":"kids-dance-party","name":"kids dance party","artists":[{"name":"Cupid","id":"0lax1ZgWclW6mZFaGu27MM"},{"name":"BeatBo","id":"0hpFvOQB4A7Izba40awb6Y"},{"name":"Casper & Col'ta","id":"3mWhHh5X42WmVx7Hku1zc3"},{"name":"Kids Dance Party","id":"1fgvh9SD7beKdaE8v4LWOn"},{"name":"Electric Slide Music Makers","id":"1VCtMJoDuOXAqX0rVG8xCe"},{"name":"Ray Remesch","id":"7KDvtBzHoXz3snZRFillze"},{"name":"Christopher Zondaflex Tyler","id":"5rRb6KwJPGW9sLXqRfqfgi"},{"name":"The Fresh Beat Band","id":"7oB2HtJV1OC4lrAITFO0GG"},{"name":"Chicken Dance Mix DJ's","id":"0bD4u6CHndn0nXJe8RR9xY"},{"name":"Chicken Dance","id":"3AH6sTUCngxmwaizGbhJEv"},{"name":"Ultimate Party Mixers","id":"5O5oACQgv32YxKjqazYoMK"},{"name":"Line Dances","id":"3uEmRaxWzaiK9abdGZBPRI"},{"name":"Kids Rock Kidz","id":"6CmyHNm8Nhkxaqhs31DABo"},{"name":"Preschool Popstars","id":"7r7msCm1sJiCUv2FxarTUF"},{"name":"Cha Cha Slide DJ's","id":"7dwkvomsDEwCLu7LBMiioy"},{"name":"Boston Soundlabs","id":"5041wCLttayhcfPGMJytPS"},{"name":"Kiddie Boppers","id":"6WRzEawI3M5zv3hm3OAwd0"},{"name":"Hokey Pokey Kids","id":"77coaSUYJ8DUCvcDmK98Ww"},{"name":"Limbo Rock Kids Party","id":"5Mtwfzsnnoui0egwH3OsKD"},{"name":"Freeze Dance DJ's","id":"2vnlIUooL0M6u8zJaJImU9"}],"related":["military cadence"]}