{"slug":"latino-comedy","name":"latino comedy","artists":[{"name":"John Leguizamo","id":"26nStRV6Waedt17W4Uhx6l"},{"name":"George Lopez","id":"6emrXi84Xjdb8YcEm82XEZ"},{"name":"Gabriel Iglesias","id":"4mB2yDrWdUxy5tISyQPvpu"},{"name":"Chingo Bling","id":"7uWSNqvFk0TnPO9zKbzLI5"},{"name":"Joey \"CoCo\" Diaz","id":"7gSyKYCwGoRMQQGP97GotT"},{"name":"Pablo Francisco","id":"3Ac7ymYqL8NMoyhuU6vrNJ"},{"name":"Andrew Santino","id":"7DcIffPhehwXCOHZyE5GZy"},{"name":"Anjelah Johnson","id":"5uM0Xhxwo3D632eVABcctF"},{"name":"Erik Griffin","id":"6gKCTW4sL315OU3frk7QGe"},{"name":"Felipe Esparza","id":"1BWtb7IuUhbGiXGhQ6ISzn"},{"name":"Steve Treviño","id":"12IMfzOnhQGX8Al6Xger3F"},{"name":"Willie Barcena","id":"6BgfY43zIGLDolD4Tx7zLy"},{"name":"Joey Diaz","id":"6QI5QdV0rU7Jc2JRTRtMHv"},{"name":"Bill Santiago","id":"4HNsynZFgCgMeIxoKYIufj"},{"name":"Paul Rodriguez","id":"0sTep1P5VengUk10M2v4QC"},{"name":"Jeff Garcia","id":"50Cpd6bnZyGcFvklW6sJBX"},{"name":"Joey Medina","id":"4GcY9IJlGz1gP6SczWFsPr"},{"name":"Rudy Moreno","id":"6sqwOrUYMQv7OzgZy7FT2Y"},{"name":"Cristela Alonzo","id":"1V8brWH6fBvffJrkeVVHuv"},{"name":"Greg Giraldo","id":"10qBkc8lLi41AsFmvEqa3x"}],"related":["clean comedy","australian comedy","black comedy","canadian comedy","comedy","dansk comedy","deep comedy","dutch cabaret","magyar kabare","vlaamse cabaret"]}