{"slug":"neon-pop-punk","name":"neon pop punk","artists":[{"name":"All Time Low","id":"46gyXjRIvN1NL1eCB8GBxo"},{"name":"A Day To Remember","id":"4NiJW4q9ichVqL1aUsgGAN"},{"name":"Simple Plan","id":"2p4FqHnazRucYQHyDCdBrJ"},{"name":"Jimmy Eat World","id":"3Ayl7mCk0nScecqOzvNp6s"},{"name":"The All-American Rejects","id":"3vAaWhdBR38Q02ohXqaNHT"},{"name":"Good Charlotte","id":"5aYyPjAsLj7UzANzdupwnS"},{"name":"Against The Current","id":"6yhD1KjhLxIETFF7vIRf8B"},{"name":"Sleeping With Sirens","id":"3N8Hy6xQnQv1F1XCiyGQqA"},{"name":"The Red Jumpsuit Apparatus","id":"1SImpQO0GbjRgvlwCcCtFo"},{"name":"Plain White T's","id":"1g1yxsNVPhMUl9GrMjEb2o"},{"name":"Taking Back Sunday","id":"24XtlMhEMNdi822vi0MhY1"},{"name":"The Used","id":"55VydwMyCuGcavwPuhutPL"},{"name":"Waterparks","id":"3QaxveoTiMetZCMp1sftiu"},{"name":"Escape the Fate","id":"5ojhEavq6altxW8fWIlLum"},{"name":"Bowling For Soup","id":"5ND0mGcL9SKSjWIjPd0xIb"},{"name":"BOYS LIKE GIRLS","id":"0vWCyXMrrvMlCcepuOJaGI"},{"name":"Mayday Parade","id":"3WfJ1OtrWI7RViX9DMyEGy"},{"name":"Story Of The Year","id":"0KDuKk6YdEu3hR56HtXmxt"},{"name":"Silverstein","id":"1Tsag5J854qxeOo2apszug"},{"name":"We The Kings","id":"3ao3jf5d70Tf4fPh2bnXVl"}],"related":["pop punk","pop emo","pixie","screamo","alternative pop rock","piano rock","emo","post-hardcore","electropowerpop","pop rock","metalcore","post-grunge","taiwan punk","mexican pop punk","italian pop punk","swedish melodic rock","texas pop punk","j-pixie","swedish alternative rock","gothic alternative"]}