{"slug":"progressive-deathcore","name":"progressive deathcore","artists":[{"name":"Currents","id":"5pqvAI85RMxL9K0xHvSwGu"},{"name":"Spite","id":"2DynE7m1BMVl4hQMvCXXq0"},{"name":"Varials","id":"6EFV3PmaXblKwNbvpkGv9l"},{"name":"Signs of the Swarm","id":"0yxJx8OEyDfd7dzLsFuNrS"},{"name":"Distant","id":"7dfpBi0QvO9FmlhBK6XHwJ"},{"name":"To The Grave","id":"3jr9qsKWQjf3iMNQ3rWVDQ"},{"name":"Bodysnatcher","id":"2tCl0ipvwJJRJLAuIGf6tm"},{"name":"Traitors","id":"1GkXxneFQE4d5YTsrbN6Ya"},{"name":"Mental Cruelty","id":"2iE1NqruxoSxTvOpTCLkE9"},{"name":"Filth","id":"4v3LXseeTJyL6GVDS2N8oY"},{"name":"Enterprise Earth","id":"1l3cAmALCtGbjWGVtRwhoh"},{"name":"Distinguisher","id":"2SAUkgFRLdVSLxMzT85HSc"},{"name":"Hive","id":"5DA5dDq3y1s10tuBK4HVn6"},{"name":"Reflections","id":"0DTH9zFyvRb24bb8XN0iEr"},{"name":"Before I Turn","id":"6oAHBPNjkdXwcdt2AgJgan"},{"name":"Gravemind","id":"2GaM9ww6p0aBZ8omjfINAH"},{"name":"The Last Ten Seconds of Life","id":"3AESf0xMv9HSc3svVqypnY"},{"name":"Black Tongue","id":"5vTCEZ15eybRnoqUAra4Ys"},{"name":"Crown Magnetar","id":"0DlST2L7efoM5Lb0uxG3Tx"},{"name":"Aversions Crown","id":"6OITsYO1BqjC0VIF6yGFOc"}],"related":["deathcore","slamming deathcore","downtempo deathcore","symphonic deathcore","brutal deathcore","blackened deathcore","melodic deathcore","metallic hardcore","melodic metalcore","thall","christian deathcore","german death metal","technical melodic death metal","american melodeath","german melodeath","technical deathcore","swedish melodeath","polish metalcore","slovenian metal","taiwan metal"]}