{"slug":"ukhc","name":"ukhc","artists":[{"name":"Guilt Trip","id":"07mhRucOGu6NJvRNVzqoxU"},{"name":"God Complex","id":"4Ase9pfG4FCMoiuyRduc8k"},{"name":"Desolated","id":"4aJzQA930qk1ZLTxZDllh6"},{"name":"Employed To Serve","id":"58d50jBQXhOetEGuSBgu64"},{"name":"Higher Power","id":"6yv0Vd63iiAaW4665Cs9vT"},{"name":"Ithaca","id":"7HIvrtPrTTxXrBeJkiRj8x"},{"name":"Cauldron","id":"0NFF2BJlMNVyOTY02bGbZP"},{"name":"Grove Street","id":"41hQlpi3r8ljXeRYbHbUBD"},{"name":"Last Wishes","id":"3F7BJAURMH1i94fpntbDeQ"},{"name":"Going Off","id":"2xCCFcGLx1oUlS1AMtfBo9"},{"name":"Old Wharf","id":"0VKGJBAmsWIfgP7XeN1SEi"},{"name":"Gassed Up","id":"4htJmA4WzMfJzZD5WAvD1R"},{"name":"TRC","id":"56FWp4djoIWzcpgm4AQ5G6"},{"name":"Mourning","id":"3ETfEcDsM21qIaGVzJdNUp"},{"name":"Brutality Will Prevail","id":"3Lrq7jnwOegUxvOYbd49fw"},{"name":"Mingle Harde","id":"7aB2qIy9rv5vXYTAV2wdmI"},{"name":"Violent Reaction","id":"0Wn6xj1isDvaGvMCWONxWr"},{"name":"Dead Swans","id":"5Molbqetc1WsKY3oPKTj88"},{"name":"The Ghost Of A Thousand","id":"7uw1sdrPQ0KF1BqLdz3wWA"},{"name":"The Flex","id":"1aU7iYWYKvGWgDkGqxABQz"}],"related":["uk beatdown","turkish hardcore","texas metal","chilean metal","modern hardcore","slc hardcore","metal","caribbean metal","metal mineiro","metal paraguayo","texas hardcore","cleveland metal","australian thrash metal","north carolina metal","old school thrash","metallic hardcore","mexican metal","puerto rican metal","mexican thrash metal","kentucky metal"]}