{"slug":"australian-americana","name":"australian americana","artists":[{"name":"The Teskey Brothers","id":"2nTjd2lNo1GVEfXM3bCnsh"},{"name":"Kasey Chambers","id":"6uATIQFyydDXPc2RlLzcUE"},{"name":"Shane Nicholson","id":"2VGE8KFAYM3yE0qOsDGf6t"},{"name":"WILSN","id":"2ymjQZjPQe0pziQ67Y8Ncr"},{"name":"Catherine Britt","id":"2U7nIOFSqqsKaBdSIdL0iZ"},{"name":"Tori Forsyth","id":"0UVISIZtASrGYL3975rp6w"},{"name":"William Crighton","id":"4EVBuMQ6XVgxeqWKH09dBM"},{"name":"Brian Cadd","id":"7DZDByO8dEuOb1V5JcJPfI"},{"name":"Fanny Lumsden","id":"4WxHef1Si5yaAaCWUc6Ug2"},{"name":"Andrew Swift","id":"428gAQRnMEaxHVT0VoUNCd"},{"name":"Oh Pep!","id":"3L9rqEIsNSaOcx2QIstn7v"},{"name":"Falls","id":"0SP0jz4htYhpiCuNEvKr0l"},{"name":"Clare Bowen","id":"1LBeAxaCAHECiK355bwtlW"},{"name":"Liz Stringer","id":"1pQUWntaZHuboOtD9Gfel2"},{"name":"Tom West","id":"4IszB4IvfBur47pa0bm1sr"},{"name":"Jordan Merrick","id":"0ahcACj3s9GCO561Tja3Mj"},{"name":"The Audreys","id":"4YhCaFhYdUaPihkxTqEtkZ"},{"name":"Matt Joe Gow","id":"7eQmpykA7m2nfFShPLWCgR"},{"name":"Josh Rennie-Hynes","id":"3YRZWrA1WzMaDfOPoQVHCp"},{"name":"James Kenyon","id":"5VKa6LMAotsyyKxT0NMQ5D"}],"related":["australian country","nashville americana","austin singer-songwriter","queer country","austin americana","israeli singer-songwriter","dutch americana","deep latin christian","a cappella","western americana","lilith","west bengali pop","deep indie singer-songwriter","new americana","laulaja-lauluntekija","acoustic pop","novos talentos brasileiros","kentucky roots","j-acoustic","canadian folk"]}