{"slug":"black-n-roll","name":"black 'n' roll","artists":[{"name":"Kvelertak","id":"0VE0GTaTSeeGSzrQpLmeb9"},{"name":"Darkthrone","id":"7kWnE981vITXDnAD2cZmCV"},{"name":"Satyricon","id":"221Rd0FvVxMx7eCbWqjiKd"},{"name":"Impaled Nazarene","id":"4Q7d9egO7iMngBWfgvm57d"},{"name":"Midnight","id":"28KjD5HkkDDytQzKW7JzTp"},{"name":"Abbath","id":"1epGwdbjU7JSGVBHlqptpx"},{"name":"Nattefrost","id":"6Ku1v7iIC5rxuiyBbIHc03"},{"name":"Vreid","id":"2KvwC4Kmp2U8XnKr5Yr1hm"},{"name":"Malokarpatan","id":"0ubZb5LkGMpWUps33ulYrl"},{"name":"Craft","id":"0hkIlpV0isEixFIr74VfZm"},{"name":"Wormwitch","id":"5eTTS3YDf54li8yguyoP14"},{"name":"I","id":"5E9XOlEicDpLGlRZCRarR7"},{"name":"Cloak","id":"44mrDjAyvYUG7wJZB2udrT"},{"name":"Venom Inc.","id":"3MHIoEboWZOn2vX4O3GrjM"},{"name":"Barathrum","id":"1SGvAkR4nsQoXdhHHFFuM4"},{"name":"Nachtmystium","id":"5Cz18ETgjR6kcVMUK0YOqD"},{"name":"Sabbat","id":"0jt8kceByMQRorrMxKEUUt"},{"name":"Khold","id":"1jWLZOjuzRSkIxmrqAx4Vt"},{"name":"Nocturnal","id":"4m4e8k1UPDlXtg2JETDX1g"},{"name":"Demonaz","id":"0ug84nvWi4PxvGIL52EZWr"}],"related":["black metal","black thrash","norwegian metal","black speed metal","norwegian black metal","norwegian death metal","czsk black metal","irish death metal","new wave of speed metal","maltese metal","melodic black metal","british black metal","polish black metal","greek black metal","colombian black metal","neo-crust","austrian black metal","blackened hardcore","chain punk","necrogrind"]}