{"slug":"black-thrash","name":"black thrash","artists":[{"name":"Sodom","id":"6SYbLA9utoNsllunR1TnkM"},{"name":"Bathory","id":"6rBvjnvdsRxFRSrq1StGOM"},{"name":"Kvelertak","id":"0VE0GTaTSeeGSzrQpLmeb9"},{"name":"Venom","id":"5fwaejlOHVBAw1KhIPPaQe"},{"name":"Celtic Frost","id":"4ZISAmHmQUDCpv8xydqeKG"},{"name":"Toxic Holocaust","id":"0WVXlaglIOtQueNbucPjZ0"},{"name":"Impaled Nazarene","id":"4Q7d9egO7iMngBWfgvm57d"},{"name":"Hellripper","id":"6FfZaHz07OsknWNdtdan5R"},{"name":"Sarcófago","id":"3bPSw3qkTeBZXnfDFUqmPG"},{"name":"Skeletonwitch","id":"213mmq3zkNWx7CtfzftTC5"},{"name":"Incantation","id":"66AXpP038gUcoKVQoO98Fz"},{"name":"Massacre","id":"10tKMKG6F95zDrJOxqtjhA"},{"name":"Inquisition","id":"4BXKhsgc3Bx8Etj7A128Vm"},{"name":"Archgoat","id":"3n2bgWmlyHgwnd9aPmnTM4"},{"name":"Absu","id":"3eVkhnD2UKVjX5uiUsqfXP"},{"name":"Hellhammer","id":"3FrsGZO0uosIs2Vn2TJhQY"},{"name":"Exciter","id":"1jH2JkQvdH6R63yORA8GTd"},{"name":"Sinister","id":"6rJPCPv9Nf0AeCFYCDNTZd"},{"name":"Wraith","id":"2PoKRqTdpPPNoeuLudp0yS"},{"name":"Witchery","id":"0ucuxyPTAHv0TPkA1WBV10"}],"related":["black speed metal","black metal","death metal","new wave of speed metal","black 'n' roll","black death","thrash metal","norwegian death metal","war metal","deathrash","peruvian death metal","british death metal","swedish metal","dutch death metal","deathgrind","necrogrind","brazilian death metal","singaporean metal","british black metal","brutal death metal"]}