{"slug":"caucasian-folk","name":"caucasian folk","artists":[{"name":"Sukhishvili Georgian National Ballet","id":"6flq0A69JhkXyVhIrwLACO"},{"name":"Lela Tataraidze","id":"5r7vi7uSNPBEWN3z4EWlRO"},{"name":"찼혘혷찼혘혬찼혘짖찼혘혻찼혘혬 찼혘혩찼혘혨찼혘혪찼혘혻찼혘혨찼혘짖찼혘혱찼혘혶찼혘혵 찼혘혪찼혘혻찼혘짙찼혘혯찼혘혱찼혘혵찼혘징찼혘혲찼혘혱","id":"7fdFz7Po4kxEu5OwtIousu"},{"name":"Hamlet Gonashvili","id":"7EamYGgXLPBoi4CQgHJPH2"},{"name":"The Rustavi Choir","id":"20xUp9EMM1ahw4xip6VIOi"},{"name":"찼혘혷찼혘혨찼혘혵찼혘짤찼혘혶","id":"2o2AjBx8heornc0N1a41dg"},{"name":"찼혘혻찼혘혬찼혘혮찼혘혨찼혘혯 찼혘혳찼혘혨찼혘짝찼혘혱찼혘짬찼혘혬","id":"0P5jEUlPZLLbukMPNE3WFD"},{"name":"찼혘혲찼혘혮찼혘혱찼혘혵찼혘짖찼혘혬찼혘짖찼혘혱 찼혘짙찼혘혻찼혘혴찼혘짙찼혘혳찼혘혱","id":"5mbPpBDlJogLWPxoUbi8iX"},{"name":"Kolkheti","id":"2eEqA8QFbpZFdxt1RJALbn"},{"name":"Basiani","id":"4VVJdu9Zhbx9L5vwyBhp0R"},{"name":"찼혘혨찼혘혵찼혘징찼혘혨찼혘혴찼혘혩찼혘혳찼혘혱 찼혘혲찼혘혬찼혘혳찼혘혨찼혘혷찼혘짖찼혘혨찼혘혻찼혘혱","id":"6VHhG2ecUtjgbVgnu4xg6y"},{"name":"Gori Women's Choir","id":"7BbXkJxQPnsiNI0c2XaUwL"},{"name":"Zedashe","id":"17iQqtGUW7F4VDChzRAo3K"},{"name":"Georgian Voices","id":"06oRBkR4QTwD0c5LUsmO8U"},{"name":"Bani","id":"7fl9xgb1N1U0E1IdC1bp9z"},{"name":"Ensemble Tbilisi","id":"54SIBA0Chr1a2Tiopmk10J"},{"name":"Georgian Vocal Ensemble","id":"4GSQjg6JHhOgtAcnNZzwAA"},{"name":"Trio Kavkasia","id":"3vg8KPdwJWESWNMja5Volr"},{"name":"Folk Ensemble Gurna","id":"6797jBDBVjq3sB6OU3YcBa"},{"name":"Kesane Quartet","id":"3hTrYiYxaISCTu7vHpzb4n"}],"related":["georgian folk","georgian polyphony","polyphony","women's choir","medieval ensemble","italian orchestra","chant religieux","icelandic choir","gregorian chant","italian tenor","puirt-a-beul","naturjodel","lds","latin american baroque","barockinterpreten","modern string quartet","french opera","karntner volksmusik","austrian choir","american 21st century classical"]}