{"slug":"deep-swedish-rock","name":"deep swedish rock","artists":[{"name":"Tore and the No Smokers","id":"1ZIBwzQx6atmOUIN6xxV2D"},{"name":"Lucidor","id":"4i3cy263TuOA9Az5HPJd0E"},{"name":"Nocean","id":"2wu1J0CjZj2ruGspOR3Li7"},{"name":"Grande Royale","id":"5WNH9HXRisJh4m6Qyo5iEU"},{"name":"Rubber Soul [swe]","id":"62ruBthM4chVa7AzNhuhFZ"},{"name":"ONSatan","id":"1NAUGebszRbpe96gH2L2fF"},{"name":"DiamondBack","id":"1LdifFWwOZZA5DZLyEidIN"},{"name":"Our Untold Story","id":"4vl0h0RTFaTqPbrz2G3UMd"},{"name":"Zinny Zan","id":"5eXDNE25Jhmiv9PED1x733"},{"name":"Tjänsteman & Trötte Theodor","id":"3xYOJxGoKLmCLo5VH8G92l"},{"name":"Neuros Moonshiner","id":"4NyBeVNsrxBRz5VXv9Ozo9"},{"name":"Tomas Bergsten's Fantasy","id":"5wYCaoV9dg2dg5BWkqi8RS"},{"name":"Ledjelly","id":"69rmF5tfYOE1RG6TebtzcJ"},{"name":"Gaeleri","id":"6BYKaaQ6qvvmRLMLMNoVKo"},{"name":"Odcult","id":"617H0QOLNZSIRhiCpYsmuD"},{"name":"Lost Domain","id":"3u8hgwsVFczguw7CEcTydg"},{"name":"Ocean to Burn","id":"1vau2zM7DW5WTs3DaUKBPi"},{"name":"Trashcan Dan","id":"2MxJ1CcARWnURv1gmvwYzP"},{"name":"Canis Lupus","id":"3gFfWS49HLXTWH3VefWW2g"},{"name":"Tarmgas","id":"6ApsmGYjlVM9cHSFJFHAZP"}],"related":["punk rock mexicano","rock brasiliense","brazilian emo","hard rock mexicano","varmland rock","frankfurt indie","rock catarinense","punk tuga","rock goiano","rock paraense","emo mexicano","emo","rock alternativo espanol","christian punk","canadian rock","rock pernambucano","rock cearense","welsh rock","pinoy pop punk","bali indie"]}