{"slug":"early-french-punk","name":"early french punk","artists":[{"name":"Dogs","id":"1ZiybGr2RZh2389cIOjevy"},{"name":"Kas Product","id":"54EC6gwS2xOT550t8Tqthd"},{"name":"Gazoline","id":"0jmQKrs8Mir77PffQBo0Jt"},{"name":"Starshooter","id":"3JxMeVBFcOpwRTDhmIO1e8"},{"name":"Dogs","id":"2FZdf9PSm5mejnVLHMn5jn"},{"name":"Alain Kan","id":"1Tl3IiCmOJMBmauqTxuPay"},{"name":"OBERKAMPF","id":"5xi3vFhIleCww9Qq8zbVi6"},{"name":"Marie France","id":"5ho6QpmMmHatkArsnWMDlf"},{"name":"Marie et les garçons","id":"2hpPLf0WSC2SOcQ7N58rp1"},{"name":"Stinky Toys","id":"1q1Sc2XExMNIAhd2nhLAzo"},{"name":"Charles De Goal","id":"6m0I9caUwCWyaNTzVEZGWk"},{"name":"Soggy","id":"0IIWnNCvVagnTLpoeGacjq"},{"name":"Métal Urbain","id":"01BFjzKJQLgIZFhLHH4MNp"},{"name":"Edith Nylon","id":"1qvKkovB62aQSbulp2rzkv"},{"name":"Les Olivensteins","id":"188Sg6UgTUS0ZThwrj96Ay"},{"name":"Little Bob Story","id":"4M6D1qeaVOmprO5Ga7NAPe"},{"name":"Asphalt Jungle","id":"4JDvhPrxu4z4FGK2inVvAg"},{"name":"Shakin' Street","id":"1gOSLTST5J2bcRv7u5fLjW"},{"name":"Strychnine","id":"23CaeBCkcykofgMkL7TVzo"},{"name":"Guilty Razors","id":"3QCCAIbqDcHRnthrSX4pD5"}],"related":["french post-punk","romanian punk","serbian alternative rock","queercore","galician rock","belarusian punk","rock curitibano","japanese rockabilly","rock sul-mato-grossense","russian punk","rock campineiro","turkish punk","funk metal","russian punk rock","balkan punk","hungarian rock","sonora indie","madchester","neo-proto","pirate"]}