{"slug":"edinburgh-metal","name":"edinburgh metal","artists":[{"name":"Frontierer","id":"6AMqkTWbhukzRS5je3Q5qt"},{"name":"Dvne","id":"1isrot4GGRmnqFT2vMAa5q"},{"name":"Endless Swarm","id":"0Mt971osfNFxZ3X6jqFwXf"},{"name":"Sapien","id":"18adM5rdagK55DE4mYH4aU"},{"name":"Sectioned","id":"1u7EB7U6Qs5RJK0hQJrfCn"},{"name":"Ramage Inc","id":"4xB97vKL5OxLMVEG4yRYWN"},{"name":"Iron Altar","id":"6MQMwkemI81wKGAR95r7I7"},{"name":"Dog Tired","id":"54hHvaP9y5oUGIZu5qg1wE"},{"name":"Holocaust","id":"6NwP3xfmDDnxqeLsSUzaS4"},{"name":"Tiberius","id":"3Ji0rbbKLOH8B3crNuco1f"},{"name":"Perpetua","id":"4EN0tUv2w7B5Vm7zSSnx7i"},{"name":"KING WITCH","id":"43YKLzHi1rFSnS0mCX4ujp"},{"name":"A Ritual Spirit","id":"3Qw5peDbETYbhn3nSIalkF"},{"name":"Vantage Point","id":"7tol02E2aAs5bNJR7XiolS"},{"name":"Hair of the Dog","id":"4BZ4J0nuj7ySq4RAohcrBe"},{"name":"Scumpulse","id":"7jyafuRMRDMuCbIfNfDjDK"},{"name":"Disposable","id":"3tgFHdkrLgt3ZTi43YdTTV"},{"name":"Juniper Grave","id":"3bIPYIeFY6kCRMxHngELQd"},{"name":"Bròn","id":"2FbYG178TwkuB6EABbyFxg"},{"name":"Haar","id":"7I2P0hebiHezTP9wYmP45k"}],"related":["scottish metal","utah metal","tennessee metal","new england metal","austin metal","boston metal","kentucky metal","icelandic metal","seattle metal","arkansas metal","north carolina metal","minneapolis metal","metal paranaense","birmingham metal","west virginia metal","irish metal","belgian metal","minnesota metal","uk noise rock","swedish metal"]}