{"slug":"gospel","name":"gospel","artists":[{"name":"Kirk Franklin","id":"4akybxRTGHJZ1DXjLhJ1qu"},{"name":"CeCe Winans","id":"3qfrrrSO7utFdJkM2tvMRb"},{"name":"Tasha Cobbs Leonard","id":"5YxebzzreNswbtYC1td4cx"},{"name":"Mary Mary","id":"12Kgt2eahvxNWhD5PnSUde"},{"name":"Israel & New Breed","id":"77HU1Zb1VDIFvWKteJii0E"},{"name":"Koryn Hawthorne","id":"03qM4LmPCrR7CuHTE0WAIW"},{"name":"Jonathan McReynolds","id":"5ItTHwcEtFh6DEOBheMub9"},{"name":"William McDowell","id":"6PTGRlwNbg36Mu4boWlixN"},{"name":"Travis Greene","id":"22JNV0JWTJkY1qzKJhxdRe"},{"name":"Fred Hammond","id":"2ndyVAdV9UqF1XjyTJt484"},{"name":"Tye Tribbett","id":"1xy9x7h2jKEg8iG22Sml32"},{"name":"Marvin Sapp","id":"5r0KYGxdIZEHZ6z6XbkVbo"},{"name":"Hezekiah Walker","id":"0pXt4sMs2oRnt528LTYgyd"},{"name":"Jekalyn Carr","id":"5ynRYAGjyPDE8unsFqi6MH"},{"name":"Yolanda Adams","id":"47opbYEKDjXnRk9uLscp11"},{"name":"Donnie McClurkin","id":"74IEeKcuS34kF2TjOigXra"},{"name":"Todd Galberth","id":"4EPtawsSClG1agy1MyVkMW"},{"name":"Israel Houghton","id":"7pUnaNwiKa3p27L1EwB4X6"},{"name":"Anita Wilson","id":"4rEGEwaOU6Mtdj4ylW0fjS"},{"name":"Todd Dulaney","id":"41OAtBkqAXVdMlteKlhrZz"}],"related":["gospel r&b","praise","contemporary gospel","dutch musical","german show tunes","rock of gibraltar","noel quebecois","southern gospel","classic ukrainian pop","tuna","musica sarda","classic czech pop","chanson quebecois","classic turkish pop","pop romantico","alternative country","uk americana","classic arab pop","muzica usoara","college a cappella"]}