{"slug":"hopebeat","name":"hopebeat","artists":[{"name":"The Band CAMINO","id":"6d4jrmreCmsenscuieJERc"},{"name":"Valley","id":"7blXVKBSxdFZsIqlhdViKc"},{"name":"Autoheart","id":"5Lm1CMoa8VOCBCLZesAcvc"},{"name":"Nightly","id":"3qDMrpZHtZEtVl5i1l7hP3"},{"name":"The Mowgli's","id":"6AGUQK1EWK6nvN4pLIDQDQ"},{"name":"Colony House","id":"6R664N4cEza3eORSqKSgO4"},{"name":"Smallpools","id":"4iiQabGKtS2RtTKpVkrVTw"},{"name":"Vacation Manor","id":"6lcBiGiT3dlyDMjBBtfyfS"},{"name":"Andrew McMahon in the Wilderness","id":"716ZwtZBmwROBXcFmCzfdM"},{"name":"Grizfolk","id":"6Xa4nbrSTfbioA4lLShbjh"},{"name":"joan","id":"3HXLY1sNXIxHfulrjPiRf5"},{"name":"flor","id":"0szWPxzzE8DVEfXFRCLBUb"},{"name":"Wild Party","id":"48PAAxWdIDbA4WHkHjgsEv"},{"name":"Young Rising Sons","id":"6ZUjdwG0NvY6MT7vvmluhV"},{"name":"Fran Pitcher","id":"0tYILSFSlL3nz5Z0wtW3Jf"},{"name":"The Wldlfe","id":"2Vvj76fff5uAw10W1sW54W"},{"name":"The Ivy","id":"6rwEDzogsmiJGMjUsGn8vn"},{"name":"Air Traffic Controller","id":"2Oboq4Pq88TcC9eUn2HSW9"},{"name":"Great Good Fine Ok","id":"422RLznpwUa5FsQgnTlgUH"},{"name":"The Strike","id":"6VB4TqEl0yfaF88LYHH4wj"}],"related":["indie poptimism","german pop rock","indie rockism","la pop","semarang indie","rock cristiano","canadian contemporary country","thai rock","metropopolis","indonesian pop rock","czech pop rock","euskal indie","country pop","maltese pop","shimmer pop","malang indie","african rock","classic j-pop","monterrey indie","modern country rock"]}