{"slug":"houston-indie","name":"houston indie","artists":[{"name":"The Suffers","id":"73ncl3RMnT90eLFhZdO2WU"},{"name":"Mind Shrine","id":"48UczULz1QAoYIE1bsYWgM"},{"name":"Many Rooms","id":"3WTuNU8i3JCrYEztzssnyV"},{"name":"Sam Cohen","id":"4c2FMMHkUGurATiPhTKqHP"},{"name":"Andrew James","id":"6xX1Zl1ebx9oUiIr8iK5HU"},{"name":"Buxton","id":"1qJKFe32PZgDug1xq1SVAY"},{"name":"Yellowbirds","id":"7jhLDZmwCt286VkegUD67F"},{"name":"Gio Chamba","id":"67BjZlXJIoPb5WvIQOFBgw"},{"name":"Moth Wings","id":"5uU9pWiyVLxDecrwUEkht3"},{"name":"Wild Moccasins","id":"2JwHiSpFV58C2RbrbEOgwY"},{"name":"The Tontons","id":"2NniF8bmIdc6RFp2lbZCkM"},{"name":"The Wheel Workers","id":"5lprg7DE7NnwMp2tn805rE"},{"name":"Vodi","id":"4wtwehkWul8nHCKLJNGzIG"},{"name":"Cole Hennessey","id":"7apcOcpluYQ0nHtnmErL5W"},{"name":"Ancient Cat Society","id":"4OAjTKu10hO3l5tdi3jvOn"},{"name":"Matt Harlan","id":"6lV3uGzSaiURsFWsNwZDz0"},{"name":"The Mighty Orq","id":"1fzCN7VIzEioyrbJjXVXCI"},{"name":"Twisted Wires","id":"1WexfY04d725H9XaSl7Nv4"},{"name":"Camera Cult","id":"4NpyN9BRc25e68CgiwLpXK"},{"name":"Astragal","id":"4uSP0G7AFSZRLjG6ip0WMn"}],"related":["stockholm indie","brazilian indie rock","orebro indie","dublin indie","denton tx indie","south dakota indie","new jersey indie","boston indie","dundee indie","okc indie","scottish indie","lund indie","brooklyn indie","welsh indie","indie rock","louisville indie","charlotte nc indie","seattle indie","edinburgh indie","toronto indie"]}