{"slug":"j-indie","name":"j-indie","artists":[{"name":"Saucy Dog","id":"4WqXqPmUuenMIr4QaFrZXN"},{"name":"SIX LOUNGE","id":"0hOOhY33adbUdYjrzJHYlX"},{"name":"Lucky Kilimanjaro","id":"2V8UZPMR1EbkXhzvEGBTrV"},{"name":"Kaneko Ayano","id":"4XKIIegkRbSJft0PmMv9NB"},{"name":"Mr.찾혖쨉찾혖혟찾혗혢찾혖짝","id":"4JmNcZTOHBnR8PYl4LfIX6"},{"name":"w.o.d.","id":"06sqnZl2EzpyIamhM1u3eO"},{"name":"No Buses","id":"5Tj6sv1bYiB4PqvvXcTSr6"},{"name":"Nakimushi","id":"2zv25U5N7QyNcn8I9kzZVn"},{"name":"She Her Her Hers","id":"3Th9UyipOGp08husDe0Era"},{"name":"yonige","id":"6uovEmc6Z1C1aUvvdKACXQ"},{"name":"채쨍짯챈혶혩채쩍쨀챌짤혗","id":"0illCOhPkFBykngmCWos6u"},{"name":"mei ehara","id":"7501C4PyvqS1BWbmrYq3LF"},{"name":"Hakushi Hasegawa","id":"5DZqDIAqRSN8mBM0DoQwoi"},{"name":"The fin.","id":"31zdCo7PhGXLRbg0sfBUYa"},{"name":"Yuga","id":"2QPqMxppznwSxghh3R8WrT"},{"name":"Lucie,Too","id":"5PhoNkzWUeTayL3gJv4Gvn"},{"name":"찾혖짧찾혖혥찾혖혬찾혖짢","id":"0TuzJGIGYfXb4jIlr4flYl"},{"name":"Sayonara Ponytail","id":"67FDqMJvln7C7mZLBMuu1X"},{"name":"Kegawa No Maries","id":"2x6MBpahMkXTPbtQGr27P8"},{"name":"챈혷혵챈짯짤","id":"3eFJ5DLTrkKw1kpb8gz2TS"}],"related":["japanese alternative rock","japanese indie rock","indie arequipeno","la indie","murcia indie","indie rock italiano","kyushu indie","rock independant francais","russian indie rock","bergamo indie","rock chapin","japanese indie pop","indie cantabria","belarusian indie","malang indie","cologne indie","euskal indie","detroit indie","indie veneto","rosario indie"]}