{"slug":"lagu-timur","name":"lagu timur","artists":[{"name":"Near","id":"6ojLiXkE6pfuxeb9cfY7fU"},{"name":"Wizz Baker","id":"4PUHVTv6waMpd1JUP7G6n2"},{"name":"Fresly Nikijuluw","id":"27CTGmSgvs2cUMSErJ1Thc"},{"name":"Kapthenpurek","id":"03viIgoUyg6gfAcID5hRCm"},{"name":"Justy Aldrin","id":"2U8MRFWZ3khrTlhcmWCuOC"},{"name":"Vicky Salamor","id":"12aiEPhUk121kZIkekGjNl"},{"name":"Glenn Sebastian","id":"7qQOKm4eO3eKCRbpGyOiNP"},{"name":"New Gvme","id":"24ltU5JmbqDwLUCwM7JWfv"},{"name":"M.A.C","id":"3rwqNiaXGjSupUuLYwIc8j"},{"name":"Mitha Talahatu","id":"3dj3jORpS3Y3GyzlmriQgt"},{"name":"Shine Of Black","id":"7jRbJhZZdASLFILgTin8Tt"},{"name":"DJ Qhelfin","id":"0T37oFURTpkWoGcWHjEcbR"},{"name":"Ona Hetharua","id":"1BGc4YCX6U5kgJSwvNXE72"},{"name":"Toton Caribo","id":"0v1axjG0KwIz3aciZffFMu"},{"name":"Omcon SB","id":"4IZ35TKvLNNaGZac96ozab"},{"name":"Bagarap","id":"0LCwfOzWbr6812E7ioa33B"},{"name":"Anak Kompleks","id":"1xfhnAk1ou6wAyLhen1LXF"},{"name":"Mollucan","id":"69vSf27YOnnHJbwdD1Qmie"},{"name":"Whllyano","id":"3c3oTqltLJCzqPNqgcYvGN"},{"name":"Aldo Bz","id":"3nEYSiH8DwMKTgOSGbD0SZ"}],"related":["hip hop timur","thai viral pop","indonesian viral pop","lao pop","turkish trap pop","chinese melodic rap","arunachal indie","pinoy r&b","ukrainian viral pop","northeast indian hip hop","sad rap","dytyachi pisni","vietnamese melodic rap","scandinavian r&b","afro r&b","yakut pop","pop lgbtq+ brasileira","malay rap","trap triste","telugu indie"]}