{"slug":"lounge","name":"lounge","artists":[{"name":"Frank Sinatra","id":"1Mxqyy3pSjf8kZZL4QVxS0"},{"name":"Michael Bublé","id":"1GxkXlMwML1oSg5eLPiAz3"},{"name":"Nat King Cole","id":"7v4imS0moSyGdXyLgVTIV7"},{"name":"Dean Martin","id":"49e4v89VmlDcFCMyDv9wQ9"},{"name":"Bing Crosby","id":"6ZjFtWeHP9XN7FeKSUe80S"},{"name":"Brenda Lee","id":"4cPHsZM98sKzmV26wlwD2W"},{"name":"Tony Bennett","id":"2lolQgalUvZDfp5vvVtTYV"},{"name":"Nancy Sinatra","id":"3IZrrNonYELubLPJmqOci2"},{"name":"Frankie Valli","id":"3CDKmzJu6uwEGnPLLZffpD"},{"name":"Burl Ives","id":"0MHgLfmQdutffmvWe5XBTN"},{"name":"Frankie Valli & The Four Seasons","id":"6mcrZQmgzFGRWf7C0SObou"},{"name":"Bobby Darin","id":"0EodhzA6yW1bIdD5B4tcmJ"},{"name":"Astrud Gilberto","id":"5rX2c1zow6hCph8PnnU3kF"},{"name":"Pink Martini","id":"6KyUat70qaniuiZq63HzFZ"},{"name":"Doris Day","id":"3ESG6pj6a0LvUKklENalT6"},{"name":"Glenn Miller","id":"2aAHdB5HweT3mFcRzm0swc"},{"name":"The Ink Spots","id":"5bOsFzuJ6QZMr86ezC4oXY"},{"name":"Herb Alpert & The Tijuana Brass","id":"09L3cUdx0hq6qn5bKuJJ4I"},{"name":"Harry Connick, Jr.","id":"6u17YlWtW4oqFF5Hn9UU79"},{"name":"Louis Prima","id":"52lBOxCxbJg0ttXEW9CQpW"}],"related":["exotica","adult standards","easy listening","vocal jazz","vintage broadway","swing","vintage italian pop","russian romance","spirituals","torch song","vintage finnish jazz","yunnan traditional","rabindra sangeet","broadway","korean minyo","nova canco","russian folk","vintage schlager","canti alpini","mazandarani folk"]}