{"slug":"mandopop","name":"mandopop","artists":[{"name":"Jay Chou","id":"2elBjNSdBE2Y3f0j1mjrql"},{"name":"JJ Lin","id":"7Dx7RhX0mFuXhCOUgB01uM"},{"name":"Eason Chan","id":"2QcZxAgcs2I1q7CtCkl6MI"},{"name":"Eric Chou","id":"5fEQLwq1BWWQNR8GzhOIvi"},{"name":"G.E.M.","id":"7aRC4L63dBn3CiLDuWaLSI"},{"name":"Mayday","id":"16s0YTFcyjP4kgFwt7ktrY"},{"name":"告五人","id":"6xErgeZYatiaQ36SB5bvi8"},{"name":"Joker Xue","id":"1cg0bYpP5e2DNG0RgK2CMN"},{"name":"Jolin Tsai","id":"1r9DuPTHiQ7hnRRZ99B8nL"},{"name":"Stefanie Sun","id":"0SIXZXJCAhNU8sxK0qm7hn"},{"name":"Ronghao Li","id":"0rTP0x4vRFSDbhtqcCqc8K"},{"name":"高爾宣 OSN","id":"4TcOznbEZBqev21LzAH4KE"},{"name":"Tanya Chua","id":"376pcuw4IgWBMOUwCr8kIm"},{"name":"A-Mei Chang","id":"6noxsCszBEEK04kCehugOp"},{"name":"理想混蛋","id":"0Awqm7GXGiBp8fJNGvywra"},{"name":"A-Lin","id":"28gf2piFx6cAKOMIwcky5a"},{"name":"Fish Leong","id":"3aIDSTKS9yH745GUQBxDcS"},{"name":"David Tao","id":"40tNK2YedBV2jRFAHxpifB"},{"name":"Cyndi Wang","id":"3AroL2oDPiAnMpTmIQv3KP"},{"name":"WeiBird","id":"7y3HnWCFEvWj4KM9GFSkiX"}],"related":["taiwan pop","taiwan singer-songwriter","malaysian mandopop","mainland chinese pop","classic mandopop","singaporean mandopop","taiwan indie","taiwan idol pop","cantopop","indonesian pop","lai hla","russian ccm","folk-pop","taiwanese pop","pop quebecois","finnish worship","neo mellow","british country","cape breton indie","japanese singer-songwriter"]}