{"slug":"math-rock-latinoamericano","name":"math rock latinoamericano","artists":[{"name":"Fiesta Bizarra","id":"4LJsadS7NTK4pjcXkNu5Zu"},{"name":"Sad Saturno","id":"4skcssepAWMUywr7Nmng2d"},{"name":"Kjjjjjjjjj","id":"41H3nsLvw0N1Z8FBov2Jgd"},{"name":"tortuganónima","id":"0jsPe8wkYOMs1yd3zd2aRR"},{"name":"Angelo Con Baja Autoestima","id":"15eh6gwszLI2pu628n0nRx"},{"name":"Procrastinación 1 Yo 0","id":"1MSazhd5p3dgnK1WBLduaT"},{"name":"Zeta","id":"6syYSX0eLH4srCtXhUEMXD"},{"name":"Plug Plug","id":"37dgHYWQnqCao1yZ4AqJei"},{"name":"Tenchio","id":"3fHir0WFSqzNUxeKQUKFYx"},{"name":"archipiélagos","id":"2PRjdrnN3crdykcsLu1S6d"},{"name":"Wanderlust","id":"3hacWq1eA8akZcZmmUNbOY"},{"name":"Un Viejo Arcoiris","id":"2DmfnifKTOqFOMBBj7pPbb"},{"name":"Jean Loup","id":"5u1Kdzzcl9FcgY7ty8Du0U"},{"name":"Helices","id":"1eyGv5vUAQZ85vT3rR4t28"},{"name":"Puerto Austral","id":"4PeFo2mhFvz9CeURn4nQ5o"},{"name":"Corriendo","id":"1PL7VVHo2DOSgg3Ak6S29w"},{"name":"Cecimonster vs. Donka","id":"1VsUpYfxYFg2WtGxrrJHDd"},{"name":"Incendios Forestales Del Viejo Continente","id":"2mwdGkikTTeufyEPUFRijJ"},{"name":"Kinder","id":"6Pan5A16TZ1aKMIpnePAZ9"},{"name":"LEÑA","id":"3A3FoilKOXzYIkHm948iBS"}],"related":["post-rock latinoamericano","peruvian indie","metal guitar","spanish progressive rock","shred","british math rock","austrian stoner rock","spanish psychedelic rock","brazilian lo-fi rock","psicodelia mexicana","jazz metal","canadian post-punk","polish noise rock","chinese post-punk","deep space rock","garage psych","canadian psychedelic rock","popgaze","instrumental stoner rock","italian post-hardcore"]}