{"slug":"melodic-progressive-metal","name":"melodic progressive metal","artists":[{"name":"Teramaze","id":"37Pf9riF70VuuPMXP4kz3J"},{"name":"Darkwater","id":"3VFAEJuUQ6rHfKT9qlZ3Zq"},{"name":"Signum Regis","id":"0ikl8u2xTTRCUeanIAW1mt"},{"name":"Vanishing Point","id":"3zmUekFSR8SzvgTgpIIM8j"},{"name":"Soul Secret","id":"1lrRKgENSA3wSJ4VECfrC5"},{"name":"Lalu","id":"5GmEuYwdFxc1bdl8Id3m7e"},{"name":"Paralydium","id":"65X6T9OJ2gXGpkc1DgrYgR"},{"name":"Beyond Twilight","id":"7JdZtzWCcDC43EXParGMgm"},{"name":"Ray Alder","id":"0xcZhWG8w7XvCUtziZCu09"},{"name":"Beyond the Bridge","id":"5IDfyDPRpDEGF9qxcdy5mo"},{"name":"Spheric Universe Experience","id":"3CcaI2coIsE7MMLudLbPvq"},{"name":"Lost In Thought","id":"1eaEhax0Mj4NNXxvWEtnUF"},{"name":"Noveria","id":"1mWXMFoDJAYWg1wrqUKBpE"},{"name":"Oblivion Protocol","id":"0lmulijxo9giYRfrZ8yrTr"},{"name":"Communic","id":"56w3AIFmUXAMlij4gvgEMF"},{"name":"Sunburst","id":"1gr1vOmkKj6iNS9G5lp3F2"},{"name":"Eldritch","id":"2Ike8cRSD6AOx7nCZ865RK"},{"name":"Hemina","id":"1DuzOaU8hyIpzzRQFpAO9b"},{"name":"Elegy","id":"2obAXXK0YfZo4fsFR5h2KM"},{"name":"Cloudscape","id":"0Uou3cDsitisumMuevy8OY"}],"related":["progressive power metal","italian progressive metal","swedish progressive metal","progressive metal","russian metal","mexican power metal","italian folk metal","lapland metal","fallen angel","slayer","metal uruguayo","indonesian emo","christian power metal","indonesian post-hardcore","gothic symphonic metal","progressive post-hardcore","brazilian progressive metal","italian power metal","german metal","brazilian power metal"]}