{"slug":"metal-noir-quebecois","name":"metal noir quebecois","artists":[{"name":"Spectral Wound","id":"3i6zP2x9GMBV3WyRzqQtM6"},{"name":"Akitsa","id":"0CTKq7arHzG8F0ToHBW8qj"},{"name":"Nordicwinter","id":"57eLubqPTZkDXghysW01Qj"},{"name":"Ifernach","id":"4OSPtOO4hNljpKoi4YN1Is"},{"name":"Csejthe","id":"1RJoDmwPH3PK2VOytxktkH"},{"name":"Gevurah","id":"02V1Su6xHUb5qN7fKcUkgh"},{"name":"Sorcier Des Glaces","id":"1OiVufZZzQmv0nJjzxTmia"},{"name":"Profane Order","id":"1SKfW51Tq7Cgl4xtZv9fDt"},{"name":"Cantique Lépreux","id":"0wmguM6RhXVAX7jqWWCQlK"},{"name":"Saccage","id":"6s9musa2nmjDt1XXWjdKiK"},{"name":"Strigampire","id":"56CdoDVe4SMPTqSr7rfYwv"},{"name":"Anna Pest","id":"2c9Q4bhCMbRhYyDz1Ln5IP"},{"name":"Blinded by Faith","id":"3H954WzM1VA30AxQGKgYYD"},{"name":"Monarque","id":"2avOLNGkOjuInyb2VaudUx"},{"name":"Incandescence","id":"6JKPiXuJe0yme9mqjWTGHP"},{"name":"Keys of Orthanc","id":"0EJXgnKVop5LGQgi0WviV7"},{"name":"Hak​-​Ed Damm","id":"5VMLlqXArr2gkSVQXChmVi"},{"name":"Grimoire","id":"4xiNUIvxHMuoDrziFSsISV"},{"name":"Obscurcis Romancia","id":"3VJ42M7AMhxOlBWEn69GKg"},{"name":"Valfreya","id":"7ntTUKRSVqkSzJ9521moUG"}],"related":["quebec death metal","polish black metal","greek black metal","swedish black metal","canadian black metal","pagan black metal","finnish black metal","austrian black metal","baltic black metal","spanish black metal","italian black metal","native american black metal","hungarian black metal","czsk black metal","melodic black metal","deep symphonic black metal","blackened hardcore","norwegian black metal","raw black metal","medieval black metal"]}