{"slug":"musica-blumenauense","name":"musica blumenauense","artists":[{"name":"Orly","id":"1ga5jO5WHSc52U7aLHjgMu"},{"name":"Adorável Clichê","id":"4mRFZ6ovRHoxsRBE3uymPY"},{"name":"Luiz Vicentini","id":"1Z6M8Odhm81dpk6gCgwa1K"},{"name":"Tay Galega","id":"60aybzygrfnsZwUH67fnFU"},{"name":"Iuri K","id":"7jVCHoIGvfQ0PuwNJFGX5W"},{"name":"Vlad V","id":"6lkbRGT33GRNJAIMAHxve7"},{"name":"Mazin Silva","id":"35QDLWLRuQyWVg57yhZEae"},{"name":"Léo Vieira","id":"0XxePJXaakWSiVVyITL408"},{"name":"Blesstoise","id":"58UXybpoYHIEh8ZrJMMFIQ"},{"name":"Ozuê","id":"3v5BYZxLXxVFUPdcujPaQy"},{"name":"Banda NOISE","id":"0Kj3HTOKXRwryrXeFulEGR"},{"name":"John Mueller","id":"5XXV3sCLohCYsDwj1Mkytf"},{"name":"libélula em verso","id":"3U1fdBZxZ1EC6I9rvvNeAn"},{"name":"Leo Maier","id":"2f2iUylnHsUKiqKdMgoDXu"},{"name":"Mareike","id":"3IgP55qWIA1Akk6PZtLegH"},{"name":"Acidental","id":"5qojLUEAgOGejaKlY6IZfv"},{"name":"The Zorden","id":"1DRvsL90r2lY2vAEPEmQcs"},{"name":"Taunting Glaciers","id":"5toByQX23qdXJ2NSUAJE2b"},{"name":"Ahab Sealife Conservation Inc.","id":"1CbqSB4ar233zAmCJjzaOK"},{"name":"Madeixas","id":"7hV8NzgGHPYwKnx8camqsC"}],"related":["musica mallorquina","spanish folk rock","musica campineira","portuguese rock","brasilia indie","adoracion","slovak pop","channel islands indie","galego","lo star","indonesian psychedelia","argentine indie","rogaland musikk","persian rock","glee club","haitian gospel","chilean indie","rock catala","belgian rock","rock uruguayo"]}