{"slug":"musica-infantil-catala","name":"musica infantil catala","artists":[{"name":"El Pot Petit","id":"0ppZDI2m82SqnYimw7a7xj"},{"name":"SX3","id":"1IEnoJEsq3rTAz8Baatn6K"},{"name":"Dàmaris Gelabert","id":"3FGL9zcXC0ZcBFui2S9PxK"},{"name":"Bellaterra Música Ed.","id":"5LBNhmEBK9vocKg2U1YSfM"},{"name":"La Guardiola Groga","id":"4KhPNR1YMiuKcjk5VgK0f6"},{"name":"Pep Puigdemont","id":"0yRbGYdxmPwoA9sHhyg8Q9"},{"name":"En Jep i la Rita","id":"5w2ibI8NW7cDdIkbYPZgFX"},{"name":"The Penguins","id":"3jtvYbfq9GfapNH5MhNjDm"},{"name":"Lluïsa","id":"0wAs3PDzcok5Jq7Xdp1zEa"},{"name":"Xiula","id":"75Jrb42ngkh2fqfQi0O6um"},{"name":"André","id":"2N5u8gzp4pZKH0aBDaJ33q"},{"name":"Marta Canellas","id":"1juQ68pUL5cqmYMM6eK1Bh"},{"name":"Escola Catalana","id":"7rssOFH8Ftro5T4yYR8sSa"},{"name":"Ara Va De Bo","id":"55o2RM7237Ix7XXcbpXnzd"},{"name":"Jordi Tonietti","id":"1TKnsJe47nMx5NEMYZoy64"},{"name":"Roleguita & Boquerón","id":"20CEJYV0Q7EGbnVLvEMZol"},{"name":"Lali BeGood","id":"45HbN8ylTlLEtkS6SucwwX"},{"name":"Agrupació Infantil \"Ses Motxillers\"","id":"7vu1pnncksC0akQJ8ihjud"},{"name":"Mainasons","id":"2ZQffgTQE5JS8vjCl0PiJ1"},{"name":"Grup Infantil \"El Ruc Català\"","id":"6WpVS9Q3zjmORURKpUPLxn"}],"related":["musica infantil","barnemusikk","paidika tragoudia","musica piemonteisa","ainu folk","muzika l'yeladim","er ge","musica para criancas","children's folk","tongan pop","gyerekdalok","cancion infantil latinoamericana","malawian folk","waiata mo tamariki","antilliaanse folklore","nz children's music","barnmusik","kinderliedjies","musique pour enfant quebecois","musica andina"]}