{"slug":"musica-sul-mato-grossense","name":"musica sul-mato-grossense","artists":[{"name":"Marina Peralta","id":"5zL3IWBA5pdMvLUmj0Dq2O"},{"name":"A.D.Z","id":"7G63P1XnGTfAPWbFmpMq8x"},{"name":"Codinome Winchester","id":"0oxzuDPaVqVeGDKQfp36QZ"},{"name":"Macaia","id":"3B2EYNLazFL31hMcM44lEV"},{"name":"Bêbados Habilidosos","id":"5obWz23lEqbJf7dyPSGvRv"},{"name":"Guilé","id":"3LcImgfMSyblXrPbb2FeZl"},{"name":"Marcelo Brinholi","id":"2SBN9FsJnpaHfPKxoMhMEG"},{"name":"Karla Coronel","id":"11HvjEnCtj93FLq8q0CPvb"},{"name":"Thamires Tannous","id":"1SIsvO5sL7D4xrjPjWcnfA"},{"name":"GF Gahiji","id":"3hOtF6DHkFYMUyamsJHJoP"},{"name":"Lulu Mello","id":"7ip9g9Z8k5lC9L6ENtaqk8"},{"name":"Guilherme Rondon","id":"5R9gT4DZZst60zJO2eEIuA"},{"name":"João 307","id":"32qZh8f3gYBiOFpvEdw7Rs"},{"name":"Forzan","id":"1egzkI00nRc2xzsGYHYIaF"},{"name":"Paolla","id":"4b9hVnPHj0RxsIpmmSBrDL"},{"name":"Paulo Simões","id":"5LtD9YmWtStNCtfTBNiuwZ"},{"name":"CháNoise","id":"2v2w8FH4p2sw4rwlVnLYbk"},{"name":"Geraldo Espíndola","id":"4DpamiyEQYqCgFkKVUBisi"},{"name":"Curimba","id":"0Rj5o2GHFrZDxyyKcu5HEr"},{"name":"Muchileiros","id":"2NqK91LezzMtUjoB83Tiaz"}],"related":["rock sul-mato-grossense","musica caririense","talentos brasileiros","musica catarinense","boy pop","cantautora mexicana","indie cordoba","musica capixaba","pop soul","musica paraibana","cambodian pop","nova musica maranhense","malayalam pop","musica piauiense","portuguese pop","oaxaca indie","adoracion pentecostal","musica potiguar","musica juiz-forana","malayalam worship"]}