{"slug":"polish-thrash-metal","name":"polish thrash metal","artists":[{"name":"Vader","id":"2s5DSt9VBNzAn2TbtDHzFZ"},{"name":"Acid Drinkers","id":"04bDWf1u7HxKdskC3N2nIk"},{"name":"Turbo","id":"1hT8ADv3IA415PjBUwfLLv"},{"name":"Twoyastara Of Death","id":"2ao1pKWNrHE1jRtR799tPO"},{"name":"Kat & Roman Kostrzewski","id":"1OLAjeJxTKHUFhiH5m5wAS"},{"name":"Tester Gier","id":"1XRgtKq9tGb55kvkcVxBzC"},{"name":"Tassack","id":"1bTvJqnUgGrlgfSryMpLaD"},{"name":"Witchmaster","id":"7IQL0CRtzXyFXpfWGo3tlu"},{"name":"Virgin Snatch","id":"6HewxqxH72wnR1r9f0CSQu"},{"name":"RAGEHAMMER","id":"03ohDYwWFrXfgp0VEtSTiF"},{"name":"Extinkt","id":"41rVM83IAwiQifj2ZK6mTf"},{"name":"Terrordome","id":"2Q0YzbRdbFeFRJppJLl8fd"},{"name":"Wolf Spider","id":"1jkbvjg6emc6BmISf7vaQW"},{"name":"Alastor","id":"3WAHU1esd1XJE8jASPWOmK"},{"name":"Rootwater","id":"1xax9TTO7q1fJGygVRCwrn"},{"name":"Thermit","id":"56hwmboDjX1CXJVEjaK3HZ"},{"name":"Pneuma","id":"6jNosBBrsydtFRum4LgZao"},{"name":"Horrorscope","id":"2uWJKRRSFexApEtk0bbHqL"},{"name":"Species","id":"0jNazjS70CqpEdXWBxVPEi"},{"name":"Saratan","id":"5HMCSI623hUOLhZCLJQzhk"}],"related":["polish metal","german thrash metal","metal gaucho","french hardcore","melodic thrash","atlanta metal","groove metal","speed metal","metal galego","progressive groove metal","wisconsin metal","portuguese hardcore","metal catarinense","cleveland metal","nz hardcore","brazilian metal","indonesian metal","deathcore","melodic metalcore","christian deathcore"]}