{"slug":"rap","name":"rap","artists":[{"name":"Drake","id":"3TVXtAsR1Inumwj472S9r4"},{"name":"Travis Scott","id":"0Y5tJX1MQlPlqiwlOH1tJY"},{"name":"Kanye West","id":"5K4W6rqBFWDnAN6FQUkS6x"},{"name":"SZA","id":"7tYKF4w9nC0nq9CsPZTHyP"},{"name":"Eminem","id":"7dGJo4pcD2V6oG8kP0tJRR"},{"name":"21 Savage","id":"1URnnhqYAYcrqrcwql10ft"},{"name":"Post Malone","id":"246dkjvS1zLTtiykXe5h60"},{"name":"Future","id":"1RyvyyTE3xzB2ZywiAwp0i"},{"name":"Metro Boomin","id":"0iEtIxbK0KxaSlF7G42ZOp"},{"name":"Kendrick Lamar","id":"2YZyLoL8N0Wb9xBt1NhZWg"},{"name":"J. Cole","id":"6l3HvQ5sa6mXTsMTB19rO5"},{"name":"Juice WRLD","id":"4MCBfE4596Uoi2O4DtmEMz"},{"name":"Chris Brown","id":"7bXgB6jMjp9ATFy66eO08Z"},{"name":"Lil Baby","id":"5f7VJjfbwm532GiveGC0ZK"},{"name":"Playboi Carti","id":"699OTQXzgjhIYAHMy9RyPD"},{"name":"Jack Harlow","id":"2LIk90788K0zvyj2JJVwkJ"},{"name":"Brent Faiyaz","id":"3tlXnStJ1fFhdScmQeLpuG"},{"name":"Lil Uzi Vert","id":"4O15NlyKLIASxsJ0PrXPfz"},{"name":"Tyler, The Creator","id":"4V8LLVI7PbaPR0K2TGSxFF"},{"name":"Gunna","id":"2hlmm7s2ICUX0LVIhVFlZQ"}],"related":["trap","pop rap","southern hip hop","hip hop","atl hip hop","gangster rap","dirty south rap","melodic rap","r&b","east coast hip hop","conscious hip hop","underground hip hop","dance pop","queens hip hop","hardcore hip hop","new orleans rap","urban contemporary","deep underground hip hop","mississippi hip hop","australian trap"]}