{"slug":"ska-catala","name":"ska catala","artists":[{"name":"La Fúmiga","id":"2Y4AiImxLUoWEgxedb3Gtz"},{"name":"Bongo Botrako","id":"6XcqNunmoXrhbq6rAYgFxJ"},{"name":"Itaca Band","id":"1tQtaouRCs37gaJVi7HTYR"},{"name":"Aspencat","id":"2cvEw5LbWVI1CspbDOgmcQ"},{"name":"Obrint Pas","id":"2FURpqYsZpi99ySpKCOyQE"},{"name":"Xavi Sarrià","id":"4PMfEsMG04n1mU3jbQGDVA"},{"name":"Agua Bendita","id":"2e3P7zO9duFmWItDELoQfq"},{"name":"Koers","id":"6EEs0hbsFGYZ3VdNOErO9n"},{"name":"Dr. Calypso","id":"6NzQGCr2sqQJ7AepiQpVGW"},{"name":"Brams","id":"0QYoTBFk6RrLqna6PfszFy"},{"name":"La Kinky Beat","id":"54fegqYOhCxElQ9RAOTroa"},{"name":"Seikos","id":"4M6VkzBYyltZ2t8AbXKLBg"},{"name":"Root Diamoons","id":"7BNUk7Gaw629fGVmoMCNsE"},{"name":"The Kinky Coo Coo's","id":"0LABm4XsKqDm0Ha30gxpAP"},{"name":"Skatalà","id":"4yU8WdZjoXlTpyxgxWyCKS"},{"name":"Muyayo Rif","id":"0k3TYsn0wPivYDhHX7HE4C"},{"name":"Los Barrankillos","id":"4tzvod2FeqFDigiG8x7UuQ"},{"name":"AlQuadrat","id":"1hs6EVB1tPjA2mjtZmznVn"},{"name":"Repúblika Ska","id":"35QWdwr5mi5FaUdP4FI7U8"},{"name":"Pastorets Rock","id":"1Jp1nIjDVFmKkz0ECuoPbJ"}],"related":["ska espanol","reggae catala","rock catala","punk catala","mestissatge","polish reggae","nagpuri pop","brazilian ska","ska chileno","indonesian ska","euroska","kolsche karneval","chechen pop","classic portuguese pop","ska argentino","montenegrin pop","geinin song","turbo folk","hungarian pop","uzbek pop"]}