{"slug":"steelpan","name":"steelpan","artists":[{"name":"Glen Velez","id":"15iQ5XT6Esaps90Qp8XlXr"},{"name":"Steel Drum Island","id":"15Bo4JfE7a3HKsw3I9En44"},{"name":"The Island Caribbean Steel Drum Band","id":"1kMdTqTrYy7FSVIoxhGFy2"},{"name":"David Rudder","id":"56LHUp2Q0S83IaayCWNavq"},{"name":"Jamaican Steel Band","id":"1NxmTb4M0OY7akmLTR079X"},{"name":"The Carnival Steel Drum Band","id":"1Ez5OXrB9MKmpJHxU6cruZ"},{"name":"Anthony Williams","id":"0FO6iwNxAbcjc8IStwizj6"},{"name":"Andy Narell","id":"5lFXWUhnMLnuubYAtgKKXa"},{"name":"Doug Walker, Steel Drum Artist","id":"2JmJEwhfiYcgLt9KhGrT9H"},{"name":"Caribbean Pirates Steel Band","id":"2tM7sFCW69cXta3h00ScAH"},{"name":"The Sunshine Sound Of The Steel Band","id":"0RAwbFfClhYmOiGlEQn7dj"},{"name":"Southside Harmonics Steel Orchestra","id":"0InUwhs6Dkt2JHabJgCgMk"},{"name":"Steel Drums Caribbean Beach Party","id":"4HLJXPVNNrk5RSMepPRuim"},{"name":"Ebony Steelband","id":"2OxUsSoC01lz0rwdslo4vV"},{"name":"Pete Lockett","id":"2gVsAD8yzjl1WQOXkrW9JB"},{"name":"Sweet Steel","id":"1I1YOxXqkEQrcVuKVLKWOt"},{"name":"Esso Trinidad Steel Band","id":"0cMTpw95Av39PkJH3VAo39"},{"name":"Barbados Steel Drums","id":"2xoK9wlFfcdZGYHasB6GV4"},{"name":"London All Stars Steel Orchestra","id":"6DXof5AfUTAYBYlPgsz8w9"},{"name":"Robert Greenidge","id":"0qLI2jjlYqBgeJqgOqJaSR"}],"related":["smooth jazz","chillhop","deep italo disco","fake","deep smooth jazz","abstract beats","afrobeat brasileiro","ambeat","ambient fusion","antilliaanse folklore","backing track","bass trip","belly dance","bossa nova jazz","brass band brasileiro","cdo indie","chill groove","chill lounge","deep chill-out","deep downtempo fusion"]}