{"slug":"sundanese-traditional","name":"sundanese traditional","artists":[{"name":"Suara Parahiangan","id":"40ZiG3vJrO9aEmPzsfsoj4"},{"name":"Indonesian Ethnic Project","id":"5miJWdi2Jv7OTTHHSRx7CQ"},{"name":"Endang Sukandar","id":"3I0Fgg40upA6RPnQ5Zmnhl"},{"name":"L. S. Kancana Sari Bandung","id":"1XghLDtUD2uDk3UqaTERkL"},{"name":"Gusti Sudarsana","id":"0ULBou2JvO37sYMEbZtuJx"},{"name":"LS Kancana Sari","id":"0dv2L0lVdA7MCYDxdZwwTn"},{"name":"Gamelan Degung","id":"6kM72nd4FOzY6rEgrIrgGp"},{"name":"Mojang Priangan","id":"2EOCAGYiv3Pr8HPcS9z0V2"},{"name":"Degung Sangkala","id":"5KOCcHLmYeqDpQTDa5mPB3"},{"name":"LS Gentra Pasundan","id":"5SOx9VUmYcWtNIEzLorLby"},{"name":"Ujang Suryana","id":"2XyIR5ahPIMP4r6Xp94wYY"},{"name":"Euis Komariah","id":"5MaQOkDQk9ROesyJY8Lor3"},{"name":"Ida Widawati","id":"5zE46ujReGTqYgnKJMYLq5"},{"name":"Gentra Pasundan","id":"5bqu5QF8vbCVlhKnJMIiAC"},{"name":"Jugala","id":"6tAPgOYjlnSonRExisWYPr"},{"name":"Tarawangsawelas","id":"4Wx6IGLGk4cI3HtL3114il"},{"name":"Ono Sukarna","id":"03xisD06nDadkOx9B5xlj5"},{"name":"Degung Sabilulungan","id":"5YBTzRqBXncZwLwZ8bYJod"},{"name":"Degung Orchestra","id":"44pvO55TsjubE0pvHmZpQ3"},{"name":"Uking Sukri","id":"1yKYWefM3tdIq0YWQdLDPV"}],"related":["gamelan","indonesian indigenous traditional","oud","choro","spanish jazz","belgian jazz","jazz catala","argentine jazz","harmonica jazz","austrian jazz","mallet","scottish jazz","guitarra portuguesa","thai traditional","slack-key guitar","jazz brass","violao","piano mpb","brazilian modern jazz","african percussion"]}